RRCF_Outlier_Detection/__init__.py
RRCF_Outlier_Detection/rrcf_outlier_detection.py
rrcf_outlier_detector_MA-0.1.0.dist-info/METADATA
rrcf_outlier_detector_MA-0.1.0.dist-info/WHEEL
rrcf_outlier_detector_MA-0.1.0.dist-info/top_level.txt
rrcf_outlier_detector_MA-0.1.0.dist-info/RECORD
