Metadata-Version: 2.1
Name: rrcf-outlier-detector-MA
Version: 0.1.0
Summary: Demo library
Home-page: https://www.moodysanalytics.com/
Author: Roberto Martinez Cruz
Author-email: roberto.martinezcruz@moodys.com
License: Moody's Analytics
Platform: UNKNOWN
Classifier: Intended Audience :: Developers
Classifier: Programming Language :: Python
Classifier: Programming Language :: Python :: 3
Classifier: Programming Language :: Python :: 3.6
Classifier: Programming Language :: Python :: 3.7
Classifier: Programming Language :: Python :: 3.8
Classifier: Programming Language :: Python :: 3.9
Classifier: Operating System :: OS Independent
Requires-Dist: numpy
Requires-Dist: pandas
Requires-Dist: rrcf
Requires-Dist: sklearn
